my_base_tkinter_app/__init__.py
my_base_tkinter_app/_app/__init__.py
my_base_tkinter_app/_app/_base_app.py
my_base_tkinter_app/_app/_error_box.py
my_base_tkinter_app/_assets/__init__.py
my_base_tkinter_app/_assets/_convert_image_to_ico.py
my_base_tkinter_app-0.1.0.dist-info/METADATA
my_base_tkinter_app-0.1.0.dist-info/WHEEL
my_base_tkinter_app-0.1.0.dist-info/top_level.txt
my_base_tkinter_app-0.1.0.dist-info/RECORD
