Metadata-Version: 2.2
Name: my_base_tkinter_app
Version: 0.1.0
Summary: My personal base app framework, based in Tkinter.
Author-email: Cody Baker <cody.c.baker.phd@gmail.com>
License: MIT License
Project-URL: Homepage, https://github.com/CodyCBakerPhD/my_base_tkinter_app
Project-URL: Bug Tracker, https://github.com/CodyCBakerPhD/my_base_tkinter_app/issues
Keywords: template,base,abstract,gui,tkinter,app
Classifier: Programming Language :: Python
Classifier: Programming Language :: Python :: 3.13
Classifier: License :: OSI Approved :: MIT License
Classifier: Operating System :: Microsoft :: Windows :: Windows 10
Classifier: Operating System :: Microsoft :: Windows :: Windows 11
Classifier: Operating System :: Unix
Requires-Python: <3.14,>=3.13
Provides-Extra: icons
Requires-Dist: pillow; extra == "icons"
Provides-Extra: dev
Requires-Dist: ipython; extra == "dev"
Requires-Dist: pre-commit; extra == "dev"
Provides-Extra: tests
Requires-Dist: pytest-cov; extra == "tests"
Requires-Dist: scikit-image; extra == "tests"
Provides-Extra: all
Requires-Dist: my_base_tkinter_app[dev,icons,tests]; extra == "all"
